README.md
setup.py
django_jsonyamlfield/__init__.py
django_jsonyamlfield/fields.py
django_jsonyamlfield.egg-info/PKG-INFO
django_jsonyamlfield.egg-info/SOURCES.txt
django_jsonyamlfield.egg-info/dependency_links.txt
django_jsonyamlfield.egg-info/requires.txt
django_jsonyamlfield.egg-info/top_level.txt